[{"timestamp":"2022-09-01T12:54:55.929Z","count":0,"uniques":0},{"timestamp":"2022-10-01T12:55:18.383Z","count":15,"uniques":3},{"timestamp":"2022-11-01T02:05:00.374Z","count":0,"uniques":0},{"timestamp":"2022-12-01T01:16:02.226Z","count":2,"uniques":1},{"timestamp":"2023-01-01T01:21:18.113Z","count":2,"uniques":1},{"timestamp":"2023-02-01T01:21:09.029Z","count":0,"uniques":0},{"timestamp":"2023-03-01T01:27:14.326Z","count":0,"uniques":0},{"timestamp":"2023-04-01T01:12:17.044Z","count":3,"uniques":1},{"timestamp":"2023-05-01T01:14:13.728Z","count":0,"uniques":0},{"timestamp":"2023-06-01T01:28:23.584Z","count":0,"uniques":0},{"timestamp":"2023-07-01T01:45:27.121Z","count":0,"uniques":0},{"timestamp":"2023-08-01T01:11:59.722Z","count":0,"uniques":0},{"timestamp":"2023-09-01T01:00:48.450Z","count":0,"uniques":0}]
