[{"timestamp":"2024-11-01T01:22:46.589Z","count":0,"uniques":0},{"timestamp":"2024-12-01T01:40:19.794Z","count":0,"uniques":0},{"timestamp":"2025-01-01T01:23:30.376Z","count":0,"uniques":0},{"timestamp":"2025-02-01T01:25:45.898Z","count":0,"uniques":0},{"timestamp":"2025-03-01T01:30:27.625Z","count":0,"uniques":0},{"timestamp":"2025-04-01T01:39:09.117Z","count":0,"uniques":0},{"timestamp":"2025-05-01T01:45:12.880Z","count":1,"uniques":1},{"timestamp":"2025-06-01T01:50:08.868Z","count":0,"uniques":0},{"timestamp":"2025-07-01T01:48:39.910Z","count":0,"uniques":0},{"timestamp":"2025-08-01T01:51:30.271Z","count":0,"uniques":0},{"timestamp":"2025-09-01T01:27:29.049Z","count":1,"uniques":1},{"timestamp":"2025-10-01T01:27:48.600Z","count":0,"uniques":0}]
