[{"timestamp":"2024-07-01T01:12:11.090Z","count":0,"uniques":0},{"timestamp":"2024-08-01T01:14:16.009Z","count":0,"uniques":0},{"timestamp":"2024-09-01T01:20:04.267Z","count":0,"uniques":0},{"timestamp":"2024-10-01T01:22:54.314Z","count":0,"uniques":0},{"timestamp":"2024-11-01T01:22:38.008Z","count":0,"uniques":0},{"timestamp":"2024-12-01T01:40:11.735Z","count":0,"uniques":0},{"timestamp":"2025-01-01T01:23:22.543Z","count":0,"uniques":0},{"timestamp":"2025-02-01T01:25:38.461Z","count":0,"uniques":0},{"timestamp":"2025-03-01T01:30:20.615Z","count":0,"uniques":0},{"timestamp":"2025-04-01T01:39:02.232Z","count":0,"uniques":0},{"timestamp":"2025-05-01T01:42:27.214Z","count":0,"uniques":0},{"timestamp":"2025-06-01T01:50:00.648Z","count":0,"uniques":0},{"timestamp":"2025-07-01T01:48:32.087Z","count":0,"uniques":0}]
